odoo/addons/l10n_es_ticketbai_oss/README.rst
odoo/addons/l10n_es_ticketbai_oss/__init__.py
odoo/addons/l10n_es_ticketbai_oss/__manifest__.py
odoo/addons/l10n_es_ticketbai_oss/data/vat_regime_key_data.xml
odoo/addons/l10n_es_ticketbai_oss/i18n/es.po
odoo/addons/l10n_es_ticketbai_oss/i18n/l10n_es_ticketbai_oss.pot
odoo/addons/l10n_es_ticketbai_oss/models/__init__.py
odoo/addons/l10n_es_ticketbai_oss/models/ticketbai_invoice_tax.py
odoo/addons/l10n_es_ticketbai_oss/readme/CONFIGURE.rst
odoo/addons/l10n_es_ticketbai_oss/readme/CONTRIBUTORS.rst
odoo/addons/l10n_es_ticketbai_oss/readme/DESCRIPTION.rst
odoo/addons/l10n_es_ticketbai_oss/readme/INSTALL.rst
odoo/addons/l10n_es_ticketbai_oss/static/description/icon.png
odoo/addons/l10n_es_ticketbai_oss/static/description/index.html
odoo/addons/l10n_es_ticketbai_oss/tests/__init__.py
odoo/addons/l10n_es_ticketbai_oss/tests/test_invoice_oss.py
odoo_addon_l10n_es_ticketbai_oss-16.0.1.0.1.dist-info/METADATA
odoo_addon_l10n_es_ticketbai_oss-16.0.1.0.1.dist-info/WHEEL
odoo_addon_l10n_es_ticketbai_oss-16.0.1.0.1.dist-info/top_level.txt
odoo_addon_l10n_es_ticketbai_oss-16.0.1.0.1.dist-info/RECORD
