Metadata-Version: 2.1
Name: odoo-addon-l10n_es_ticketbai_oss
Version: 16.0.1.0.1
Summary: TicketBAI - OSS
Home-page: https://github.com/OCA/l10n-spain
Author: Landoo Sistemas de Información S.L, Odoo Community Association (OCA)
Author-email: support@odoo-community.org
License: AGPL-3
Classifier: Programming Language :: Python
Classifier: Framework :: Odoo
Classifier: Framework :: Odoo :: 16.0
Classifier: License :: OSI Approved :: GNU Affero General Public License v3
Classifier: Development Status :: 4 - Beta
Requires-Python: >=3.10
Requires-Dist: odoo-addon-l10n-es-ticketbai<16.1dev,>=16.0dev
Requires-Dist: odoo-addon-l10n-eu-oss-oca<16.1dev,>=16.0dev
Requires-Dist: odoo<16.1dev,>=16.0a
